{
  "generated_at": "2026-03-16T19:56:13.273680+00:00",
  "unit": "EUR/MWh",
  "days": [
    {
      "date": "2026-03-11",
      "prices": [
        83.96,
        70.8,
        65.43,
        63.57,
        56.07,
        64.54,
        70.87,
        80.87,
        75.5,
        57.95,
        26.23,
        12.2,
        9.91,
        16.14,
        47.27,
        79.33,
        104.11,
        128.78,
        153.14,
        156.72,
        132.19,
        123.03,
        119.3,
        104.0
      ]
    },
    {
      "date": "2026-03-12",
      "prices": [
        100.19,
        92.04,
        88.81,
        88.61,
        89.66,
        99.82,
        130.67,
        137.14,
        104.81,
        80.0,
        28.48,
        0.34,
        -1.09,
        -2.49,
        -0.9,
        3.6,
        51.17,
        108.58,
        114.87,
        106.0,
        86.57,
        69.79,
        62.55,
        17.9
      ]
    },
    {
      "date": "2026-03-13",
      "prices": [
        6.29,
        4.1,
        2.89,
        1.15,
        1.46,
        2.91,
        8.46,
        19.94,
        6.41,
        -0.24,
        -5.0,
        -9.0,
        -8.35,
        -2.55,
        1.17,
        47.07,
        101.31,
        141.93,
        161.49,
        165.75,
        145.72,
        130.33,
        123.42,
        115.81
      ]
    },
    {
      "date": "2026-03-14",
      "prices": [
        112.95,
        109.07,
        103.99,
        101.86,
        105.12,
        109.07,
        111.52,
        116.71,
        121.88,
        116.14,
        107.52,
        103.53,
        104.2,
        103.43,
        105.68,
        114.22,
        130.0,
        138.65,
        161.1,
        169.83,
        150.27,
        137.45,
        135.24,
        128.05
      ]
    },
    {
      "date": "2026-03-15",
      "prices": [
        137.34,
        133.73,
        124.96,
        123.53,
        122.18,
        124.12,
        124.39,
        118.46,
        109.1,
        94.77,
        87.31,
        72.21,
        52.97,
        36.46,
        37.2,
        63.08,
        89.25,
        127.91,
        149.12,
        131.87,
        108.48,
        91.88,
        82.86,
        64.02
      ]
    },
    {
      "date": "2026-03-16",
      "prices": [
        34.17,
        23.33,
        17.59,
        14.14,
        20.06,
        37.43,
        66.19,
        95.57,
        95.98,
        73.1,
        42.6,
        17.37,
        12.04,
        15.88,
        42.17,
        64.45,
        106.21,
        138.6,
        165.04,
        179.89,
        154.78,
        125.71,
        121.91,
        99.77
      ]
    },
    {
      "date": "2026-03-17",
      "prices": [
        113.67,
        105.59,
        106.42,
        106.52,
        110.03,
        119.92,
        147.97,
        167.98,
        152.51,
        124.07,
        108.64,
        100.65,
        95.23,
        96.77,
        99.33,
        112.11,
        131.78,
        162.2,
        207.3,
        170.38,
        144.24,
        129.79,
        114.24,
        97.87
      ]
    }
  ]
}